{
  "code": "pre-hispanic-city-of-chichen-itza",
  "name": "Pre-Hispanic City of Chichen-Itza",
  "type": "Cultural",
  "country": "Mexico",
  "yearInscribed": "1988",
  "criteria": [
    "(i)",
    "(ii)",
    "(iii)"
  ],
  "region": "Latin America and the Caribbean",
  "description": "This sacred site was one of the greatest Mayan centres of the Yucatán peninsula. Throughout its nearly 1,000-year history, different peoples have left their mark on the city. The Maya and Toltec vision of the world and the universe is revealed in their stone monuments and artistic works. The fusion of Mayan construction techniques with new elements from central Mexico make Chichen-Itza one of the most important examples of the Mayan-Toltec civilization in Yucatán. Several buildings have survived, such as the Warriors’ Temple, El Castillo and the circular observatory known as El Caracol.",
  "danger": false,
  "geojson": "pre-hispanic-city-of-chichen-itza.geojson"
}