{
  "code": "stari-grad-plain",
  "name": "Stari Grad Plain",
  "type": "Cultural",
  "country": "Croatia",
  "yearInscribed": "2008",
  "criteria": [
    "(ii)",
    "(iii)",
    "(v)"
  ],
  "region": "Europe and North America",
  "description": "Stari Grad Plain on the Adriatic island of Hvar is a cultural landscape that has remained practically intact since it was first colonized by Ionian Greeks from Paros in the 4th century BC. The original agricultural activity of this fertile plain, mainly centring on grapes and olives, has been maintained since Greek times to the present. The site is also a natural reserve. The landscape features ancient stone walls and trims, or small stone shelters, and bears testimony to the ancient geometrical system of land division used by the ancient Greeks, the chora which has remained virtually intact over 24 centuries.",
  "danger": false,
  "geojson": "stari-grad-plain.geojson"
}